<?xml version="1.0" encoding="UTF-8" standalone="yes"?>
<AssignMessage async="false" continueOnError="false" enabled="true" name="HPX_SetResponseContentTypeToJSON">
    <DisplayName>SetResponseContentTypeToJSON</DisplayName>
    <Properties/>
    <Set>
        <Headers>
            <Header name="Content-Type">application/json+fhir;charset=UTF-8</Header>
        </Headers>
    </Set>
    <IgnoreUnresolvedVariables>true</IgnoreUnresolvedVariables>
    <AssignTo createNew="false" transport="http" type="request"/>
</AssignMessage>